line_image_extractor/__init__.py
line_image_extractor/extractor.py
line_image_extractor/image_utils.py
line_image_extractor/main.py
teklia_line_image_extractor-0.7.0.dist-info/licenses/LICENSE
teklia_line_image_extractor-0.7.0.dist-info/METADATA
teklia_line_image_extractor-0.7.0.dist-info/WHEEL
teklia_line_image_extractor-0.7.0.dist-info/entry_points.txt
teklia_line_image_extractor-0.7.0.dist-info/top_level.txt
teklia_line_image_extractor-0.7.0.dist-info/RECORD
