Metadata-Version: 2.4
Name: teklia-line-image-extractor
Version: 0.7.0
Summary: A tool for extracting a text line image from the contour with different methods
Home-page: https://gitlab.teklia.com/atr/line_image_extractor
Author: Martin Maarand
Author-email: maarand@teklia.com
Keywords: line transformation image extraction
Classifier: License :: OSI Approved :: MIT License
Classifier: Intended Audience :: Science/Research
Classifier: Programming Language :: Python :: 3
Classifier: Programming Language :: Python :: 3 :: Only
Classifier: Programming Language :: Python :: 3.8
Classifier: Programming Language :: Python :: 3.9
Classifier: Programming Language :: Python :: 3.10
Classifier: Topic :: Scientific/Engineering :: Image Recognition
License-File: LICENSE
Requires-Dist: opencv-python-headless==4.10.0.84
Requires-Dist: Pillow==11.3.0
Dynamic: author
Dynamic: author-email
Dynamic: classifier
Dynamic: description
Dynamic: description-content-type
Dynamic: home-page
Dynamic: keywords
Dynamic: license-file
Dynamic: requires-dist
Dynamic: summary
